lanarky/__init__.py
lanarky/adapters/__init__.py
lanarky/adapters/langchain/__init__.py
lanarky/adapters/langchain/callbacks.py
lanarky/adapters/langchain/dependencies.py
lanarky/adapters/langchain/responses.py
lanarky/adapters/langchain/routing.py
lanarky/adapters/langchain/utils.py
lanarky/adapters/openai/__init__.py
lanarky/adapters/openai/dependencies.py
lanarky/adapters/openai/resources.py
lanarky/adapters/openai/responses.py
lanarky/adapters/openai/routing.py
lanarky/adapters/openai/utils.py
lanarky/applications.py
lanarky/clients.py
lanarky/events.py
lanarky/logging.py
lanarky/py.typed
lanarky/responses.py
lanarky/utils.py
lanarky/websockets.py
lanarky-0.8.8.dist-info/LICENSE
lanarky-0.8.8.dist-info/METADATA
lanarky-0.8.8.dist-info/WHEEL
lanarky-0.8.8.dist-info/RECORD
