Metadata-Version: 2.1
Name: lanarky
Version: 0.8.8
Summary: The web framework for building LLM microservices
Home-page: https://lanarky.ajndkr.com/
License: MIT
Author: Ajinkya Indulkar
Author-email: ajndkr@gmail.com
Requires-Python: >=3.9,<3.12
Classifier: License :: OSI Approved :: MIT License
Classifier: Programming Language :: Python :: 3
Classifier: Programming Language :: Python :: 3.9
Classifier: Programming Language :: Python :: 3.10
Classifier: Programming Language :: Python :: 3.11
Provides-Extra: langchain
Provides-Extra: openai
Requires-Dist: fastapi (>=0.97.0)
Requires-Dist: httpx-sse (>=0.3.1,<0.4.0)
Requires-Dist: langchain (<0.3) ; extra == "langchain"
Requires-Dist: langchain-community (<0.3) ; extra == "langchain"
Requires-Dist: loguru (>=0.7.2,<0.8.0)
Requires-Dist: openai (>=1,<2) ; extra == "openai"
Requires-Dist: pydantic (>=1,<3)
Requires-Dist: sse-starlette (>=1.6.5,<2.0.0)
Requires-Dist: tiktoken (>=0.4.0,<0.5.0) ; extra == "openai"
Requires-Dist: websockets (<12.0)
Project-URL: Documentation, https://lanarky.ajndkr.com/
Project-URL: Repository, https://github.com/ajndkr/lanarky
